[
  {
    "packageName": "hgs-ui",
    "version": "latest",
    "timestamp": "2026-07-19T17:06:06.794Z"
  },
  {
    "packageName": "react-mousetrail",
    "version": "latest",
    "timestamp": "2026-07-19T17:06:06.794Z"
  },
  {
    "packageName": "omnevu-cli",
    "version": "latest",
    "timestamp": "2026-07-19T17:06:06.793Z"
  },
  {
    "packageName": "atree-react",
    "version": "latest",
    "timestamp": "2026-07-19T17:06:06.792Z"
  },
  {
    "packageName": "hrintime-base-services",
    "version": "latest",
    "timestamp": "2026-07-19T17:06:06.792Z"
  },
  {
    "packageName": "check-appname-unique",
    "version": "latest",
    "timestamp": "2026-07-19T17:06:06.791Z"
  },
  {
    "packageName": "@cropguide/browser",
    "version": "latest",
    "timestamp": "2026-07-19T17:06:06.790Z"
  },
  {
    "packageName": "@zplsw21/s2",
    "version": "latest",
    "timestamp": "2026-07-19T17:06:06.790Z"
  },
  {
    "packageName": "ras-mirror",
    "version": "latest",
    "timestamp": "2026-07-19T17:06:06.789Z"
  },
  {
    "packageName": "about-mmeester",
    "version": "latest",
    "timestamp": "2026-07-19T17:06:06.788Z"
  },
  {
    "packageName": "inview-observer.js",
    "version": "latest",
    "timestamp": "2026-07-19T17:06:06.788Z"
  },
  {
    "packageName": "vcu-charts",
    "version": "latest",
    "timestamp": "2026-07-19T17:06:06.787Z"
  },
  {
    "packageName": "gientech-madp-npm",
    "version": "latest",
    "timestamp": "2026-07-19T17:06:06.786Z"
  },
  {
    "packageName": "fujj-ui",
    "version": "latest",
    "timestamp": "2026-07-19T17:06:06.786Z"
  },
  {
    "packageName": "@smartdev1990/cronasdk1",
    "version": "latest",
    "timestamp": "2026-07-19T17:06:06.785Z"
  },
  {
    "packageName": "react-native-apple-login-ql",
    "version": "latest",
    "timestamp": "2026-07-19T17:06:06.784Z"
  },
  {
    "packageName": "akilar-candyassets",
    "version": "latest",
    "timestamp": "2026-07-19T17:06:06.784Z"
  },
  {
    "packageName": "es-minio-1",
    "version": "latest",
    "timestamp": "2026-07-19T17:06:06.783Z"
  },
  {
    "packageName": "@osas-tickets/common",
    "version": "latest",
    "timestamp": "2026-07-19T17:06:06.783Z"
  },
  {
    "packageName": "bornexcel",
    "version": "latest",
    "timestamp": "2026-07-19T17:06:06.782Z"
  },
  {
    "packageName": "sk-jsapi",
    "version": "latest",
    "timestamp": "2026-07-19T17:06:06.781Z"
  },
  {
    "packageName": "npm-test-hellooooo",
    "version": "latest",
    "timestamp": "2026-07-19T17:06:06.781Z"
  },
  {
    "packageName": "@mybricks-cloud/dhunting-supplier-change-password",
    "version": "latest",
    "timestamp": "2026-07-19T17:06:06.780Z"
  },
  {
    "packageName": "l7",
    "version": "latest",
    "timestamp": "2026-07-19T17:06:06.780Z"
  },
  {
    "packageName": "vite-plugin-lib-inject-style",
    "version": "latest",
    "timestamp": "2026-07-19T17:06:06.779Z"
  },
  {
    "packageName": "@liquidator/common",
    "version": "latest",
    "timestamp": "2026-07-19T17:06:06.778Z"
  },
  {
    "packageName": "strapi-provider-email-dabmail",
    "version": "latest",
    "timestamp": "2026-07-19T17:06:06.778Z"
  },
  {
    "packageName": "@mybricks-cloud/antd-every-version",
    "version": "latest",
    "timestamp": "2026-07-19T17:06:06.777Z"
  },
  {
    "packageName": "custorm-cm-cli",
    "version": "latest",
    "timestamp": "2026-07-19T17:06:06.776Z"
  },
  {
    "packageName": "@semi-bot/semi-theme-ceshiti",
    "version": "latest",
    "timestamp": "2026-07-19T17:06:06.773Z"
  },
  {
    "packageName": "nuxt-vanilla-extract",
    "version": "latest",
    "timestamp": "2026-07-19T17:06:06.773Z"
  },
  {
    "packageName": "datel-minu-andmed-ui",
    "version": "latest",
    "timestamp": "2026-07-19T17:06:06.772Z"
  },
  {
    "packageName": "es-minio",
    "version": "latest",
    "timestamp": "2026-07-19T17:06:06.771Z"
  },
  {
    "packageName": "@deepblu/ddd",
    "version": "latest",
    "timestamp": "2026-07-19T17:06:06.771Z"
  },
  {
    "packageName": "@bigstair2/core",
    "version": "latest",
    "timestamp": "2026-07-19T17:06:06.770Z"
  },
  {
    "packageName": "@mybricks-cloud/leo11",
    "version": "latest",
    "timestamp": "2026-07-19T17:06:06.769Z"
  },
  {
    "packageName": "create-zhiji",
    "version": "latest",
    "timestamp": "2026-07-19T17:06:06.768Z"
  },
  {
    "packageName": "aw-my-storybook-components",
    "version": "latest",
    "timestamp": "2026-07-19T17:06:06.768Z"
  },
  {
    "packageName": "npm-demp",
    "version": "latest",
    "timestamp": "2026-07-19T17:06:06.767Z"
  },
  {
    "packageName": "gis-helper",
    "version": "latest",
    "timestamp": "2026-07-19T17:06:06.766Z"
  },
  {
    "packageName": "fmihel-lazy-load",
    "version": "latest",
    "timestamp": "2026-07-19T17:06:06.765Z"
  },
  {
    "packageName": "web-ext-msg-passing",
    "version": "latest",
    "timestamp": "2026-07-19T17:06:06.765Z"
  },
  {
    "packageName": "switchservice",
    "version": "latest",
    "timestamp": "2026-07-19T17:06:06.762Z"
  },
  {
    "packageName": "@vizorous/nest-query-utils",
    "version": "latest",
    "timestamp": "2026-07-19T17:06:06.761Z"
  },
  {
    "packageName": "@webdocker/data",
    "version": "latest",
    "timestamp": "2026-07-19T17:06:06.759Z"
  },
  {
    "packageName": "@ezyaez/stylelint-config-ez",
    "version": "latest",
    "timestamp": "2026-07-19T17:06:06.758Z"
  },
  {
    "packageName": "@webdocker/vue-microapp-entry",
    "version": "latest",
    "timestamp": "2026-07-19T17:06:06.754Z"
  },
  {
    "packageName": "@webdocker/react-host-application",
    "version": "latest",
    "timestamp": "2026-07-19T17:06:06.750Z"
  },
  {
    "packageName": "@webdocker/core",
    "version": "latest",
    "timestamp": "2026-07-19T17:06:06.748Z"
  },
  {
    "packageName": "@ezyaez/eslint-config-yc",
    "version": "latest",
    "timestamp": "2026-07-19T17:06:06.746Z"
  },
  {
    "packageName": "@ezyaez/eslint-config-ez",
    "version": "latest",
    "timestamp": "2026-07-19T17:06:06.745Z"
  },
  {
    "packageName": "@wzdong/evtlistener",
    "version": "latest",
    "timestamp": "2026-07-19T17:06:06.744Z"
  },
  {
    "packageName": "ds-views",
    "version": "latest",
    "timestamp": "2026-07-19T17:06:06.744Z"
  },
  {
    "packageName": "butterfly-react",
    "version": "latest",
    "timestamp": "2026-07-19T17:06:06.743Z"
  },
  {
    "packageName": "stupid-writer",
    "version": "latest",
    "timestamp": "2026-07-19T17:06:06.743Z"
  },
  {
    "packageName": "@luongtt/auth-api-middleware",
    "version": "latest",
    "timestamp": "2026-07-19T17:06:06.742Z"
  },
  {
    "packageName": "vkunje-frame-print",
    "version": "latest",
    "timestamp": "2026-07-19T17:06:06.740Z"
  },
  {
    "packageName": "@io-arc/env",
    "version": "latest",
    "timestamp": "2026-07-19T15:03:21.811Z"
  },
  {
    "packageName": "@io-arc/cli",
    "version": "latest",
    "timestamp": "2026-07-19T15:03:21.810Z"
  },
  {
    "packageName": "@ishikawa-masashi/signal",
    "version": "latest",
    "timestamp": "2026-07-19T15:03:21.810Z"
  },
  {
    "packageName": "@tidec/logger-library",
    "version": "latest",
    "timestamp": "2026-07-19T15:03:21.808Z"
  },
  {
    "packageName": "@marvinh/node-profiler",
    "version": "latest",
    "timestamp": "2026-07-19T13:39:42.742Z"
  },
  {
    "packageName": "cra-template-basic-react",
    "version": "latest",
    "timestamp": "2026-07-19T13:39:42.741Z"
  },
  {
    "packageName": "zychart",
    "version": "latest",
    "timestamp": "2026-07-19T13:39:42.740Z"
  },
  {
    "packageName": "@saraanasim/sdk-lotr",
    "version": "latest",
    "timestamp": "2026-07-19T09:58:08.379Z"
  },
  {
    "packageName": "upyog-pwc",
    "version": "latest",
    "timestamp": "2026-07-19T09:58:08.379Z"
  },
  {
    "packageName": "react-color-scheme-switch",
    "version": "latest",
    "timestamp": "2026-07-19T09:58:08.377Z"
  },
  {
    "packageName": "zart-icons",
    "version": "latest",
    "timestamp": "2026-07-18T20:58:56.657Z"
  },
  {
    "packageName": "@zhang_yong/vue-bus",
    "version": "latest",
    "timestamp": "2026-07-18T20:58:56.655Z"
  },
  {
    "packageName": "ljw-demo",
    "version": "latest",
    "timestamp": "2026-07-18T20:58:56.654Z"
  },
  {
    "packageName": "lotide_beaucoup",
    "version": "latest",
    "timestamp": "2026-07-18T17:03:58.584Z"
  },
  {
    "packageName": "@thien-trieu/lotide",
    "version": "latest",
    "timestamp": "2026-07-18T17:03:58.583Z"
  },
  {
    "packageName": "@stan-sk/lotide",
    "version": "latest",
    "timestamp": "2026-07-18T17:03:58.583Z"
  },
  {
    "packageName": "@tai-de/lotide",
    "version": "latest",
    "timestamp": "2026-07-18T17:03:58.582Z"
  },
  {
    "packageName": "@aula-ignite-ui/tokens",
    "version": "latest",
    "timestamp": "2026-07-18T17:03:58.581Z"
  },
  {
    "packageName": "@carolhcheung/lotide",
    "version": "latest",
    "timestamp": "2026-07-18T17:03:58.581Z"
  },
  {
    "packageName": "ekeyrun-topnav",
    "version": "latest",
    "timestamp": "2026-07-18T17:03:58.580Z"
  },
  {
    "packageName": "@mtourj/react-native-custom-slider",
    "version": "latest",
    "timestamp": "2026-07-18T17:03:58.579Z"
  },
  {
    "packageName": "@jhkang0724/lotide",
    "version": "latest",
    "timestamp": "2026-07-18T17:03:58.579Z"
  },
  {
    "packageName": "cordova-plugin-apple-spay",
    "version": "latest",
    "timestamp": "2026-07-18T17:03:58.578Z"
  },
  {
    "packageName": "@rqi/my-test-package",
    "version": "latest",
    "timestamp": "2026-07-18T17:03:58.577Z"
  },
  {
    "packageName": "@mtourj/skele-components",
    "version": "latest",
    "timestamp": "2026-07-18T17:03:58.576Z"
  },
  {
    "packageName": "@capwise/design-system-icons",
    "version": "latest",
    "timestamp": "2026-07-18T17:03:58.575Z"
  },
  {
    "packageName": "@rlnus/rlnsdk",
    "version": "latest",
    "timestamp": "2026-07-18T17:03:58.575Z"
  },
  {
    "packageName": "@larsyaeger/lotide",
    "version": "latest",
    "timestamp": "2026-07-18T17:03:58.574Z"
  },
  {
    "packageName": "a-djs-handler",
    "version": "latest",
    "timestamp": "2026-07-18T17:03:58.573Z"
  },
  {
    "packageName": "@xbus/auth-firebase",
    "version": "latest",
    "timestamp": "2026-07-18T17:03:58.573Z"
  },
  {
    "packageName": "mmia-editor-app",
    "version": "latest",
    "timestamp": "2026-07-18T17:03:58.572Z"
  },
  {
    "packageName": "annareuk",
    "version": "latest",
    "timestamp": "2026-07-18T17:03:58.571Z"
  },
  {
    "packageName": "@mithraic-labs/serum-remote",
    "version": "latest",
    "timestamp": "2026-07-18T17:03:58.571Z"
  },
  {
    "packageName": "m68kdecode",
    "version": "latest",
    "timestamp": "2026-07-18T17:03:58.569Z"
  },
  {
    "packageName": "@heydovetail/set",
    "version": "latest",
    "timestamp": "2026-03-31T13:59:33.988Z"
  },
  {
    "packageName": "@heydovetail/map",
    "version": "latest",
    "timestamp": "2026-03-31T13:59:33.987Z"
  },
  {
    "packageName": "@heydovetail/editorconfig",
    "version": "latest",
    "timestamp": "2026-03-31T13:59:33.987Z"
  },
  {
    "packageName": "@heydovetail/editor",
    "version": "latest",
    "timestamp": "2026-03-31T13:59:33.986Z"
  },
  {
    "packageName": "@heydovetail/dql",
    "version": "latest",
    "timestamp": "2026-03-31T13:59:33.986Z"
  },
  {
    "packageName": "@heydovetail/collector-react",
    "version": "latest",
    "timestamp": "2026-03-31T13:59:33.985Z"
  },
  {
    "packageName": "@heydovetail/assert",
    "version": "latest",
    "timestamp": "2026-03-31T13:59:33.985Z"
  },
  {
    "packageName": "@heydovetail/array",
    "version": "latest",
    "timestamp": "2026-03-31T13:59:33.984Z"
  },
  {
    "packageName": "@gzbapp/packages",
    "version": "latest",
    "timestamp": "2026-03-31T13:59:33.984Z"
  },
  {
    "packageName": "@glog/cli",
    "version": "latest",
    "timestamp": "2026-03-31T13:59:33.983Z"
  },
  {
    "packageName": "@gladysassistant/theme-optimized",
    "version": "latest",
    "timestamp": "2026-03-31T13:59:33.983Z"
  },
  {
    "packageName": "@genie-ai/genie-router",
    "version": "latest",
    "timestamp": "2026-03-31T13:59:33.982Z"
  },
  {
    "packageName": "@freestarcapital/collector-pipeline",
    "version": "latest",
    "timestamp": "2026-03-31T13:59:33.828Z"
  },
  {
    "packageName": "@forter/stylelint-config",
    "version": "latest",
    "timestamp": "2026-03-31T13:59:33.828Z"
  },
  {
    "packageName": "@forter/element",
    "version": "latest",
    "timestamp": "2026-03-31T13:59:33.827Z"
  },
  {
    "packageName": "@finn-no/toast",
    "version": "latest",
    "timestamp": "2026-03-31T13:59:33.827Z"
  },
  {
    "packageName": "@finn-no/fabric-component-classes",
    "version": "latest",
    "timestamp": "2026-03-31T13:59:33.826Z"
  },
  {
    "packageName": "@fictivekin/react-beautiful-dnd",
    "version": "latest",
    "timestamp": "2026-03-31T13:59:33.826Z"
  },
  {
    "packageName": "@fictivekin/growable-uint8-array",
    "version": "latest",
    "timestamp": "2026-03-31T13:59:33.825Z"
  },
  {
    "packageName": "@fictivekin/fk-sass",
    "version": "latest",
    "timestamp": "2026-03-31T13:59:33.825Z"
  },
  {
    "packageName": "@fictivekin/browserslist-config-fk",
    "version": "latest",
    "timestamp": "2026-03-31T13:59:33.824Z"
  },
  {
    "packageName": "@fatmatto/resultjs",
    "version": "latest",
    "timestamp": "2026-03-31T13:59:33.824Z"
  },
  {
    "packageName": "@farts/release-namer",
    "version": "latest",
    "timestamp": "2026-03-31T13:59:33.823Z"
  },
  {
    "packageName": "@fantasypoints/nunjucks-filter-moment",
    "version": "latest",
    "timestamp": "2026-03-31T13:59:33.822Z"
  },
  {
    "packageName": "@essense/iso-claim",
    "version": "latest",
    "timestamp": "2026-03-31T13:59:33.822Z"
  },
  {
    "packageName": "@epeejs/react-scroll-snap",
    "version": "latest",
    "timestamp": "2026-03-31T13:59:33.821Z"
  },
  {
    "packageName": "@eloge/utils",
    "version": "latest",
    "timestamp": "2026-03-31T13:59:33.821Z"
  },
  {
    "packageName": "@elgervb/eslint-config",
    "version": "latest",
    "timestamp": "2026-03-31T13:59:33.820Z"
  },
  {
    "packageName": "@effective/prettier",
    "version": "latest",
    "timestamp": "2026-03-31T13:59:33.820Z"
  },
  {
    "packageName": "@ecadagiani/reacttools",
    "version": "latest",
    "timestamp": "2026-03-31T13:59:33.819Z"
  },
  {
    "packageName": "@dsr-rollback-org-hover-owled-agios-situs/dsr-rollback-package-hover-owled-agios-situs",
    "version": "latest",
    "timestamp": "2026-03-31T13:59:33.818Z"
  },
  {
    "packageName": "@dragosbln/react-native-flatlist-alphabet-fixed",
    "version": "latest",
    "timestamp": "2026-03-31T13:59:33.818Z"
  },
  {
    "packageName": "@dplewis/react-material-ui-5-carousel",
    "version": "latest",
    "timestamp": "2026-03-31T13:59:33.817Z"
  },
  {
    "packageName": "@downunderctf/ducky",
    "version": "latest",
    "timestamp": "2026-03-31T13:59:33.680Z"
  },
  {
    "packageName": "@doob-ng/core",
    "version": "latest",
    "timestamp": "2026-03-31T13:59:33.680Z"
  },
  {
    "packageName": "@domp/next",
    "version": "latest",
    "timestamp": "2026-03-31T13:59:33.679Z"
  },
  {
    "packageName": "@digitalmaas/uuid-base62",
    "version": "latest",
    "timestamp": "2026-03-31T13:59:33.679Z"
  },
  {
    "packageName": "@deividfortuna/input-number",
    "version": "latest",
    "timestamp": "2026-03-31T13:59:33.678Z"
  },
  {
    "packageName": "@decoy9697/priority-queue",
    "version": "latest",
    "timestamp": "2026-03-31T13:59:33.678Z"
  },
  {
    "packageName": "@codice-progressio/express-brute-mongoose",
    "version": "latest",
    "timestamp": "2026-03-31T13:59:33.677Z"
  },
  {
    "packageName": "@chartiful/react-line-graph",
    "version": "latest",
    "timestamp": "2026-03-31T13:59:33.488Z"
  },
  {
    "packageName": "@by-association-only/concat-style-loader",
    "version": "latest",
    "timestamp": "2026-03-31T13:59:33.488Z"
  },
  {
    "packageName": "@bellini/api",
    "version": "latest",
    "timestamp": "2026-03-31T13:59:33.487Z"
  },
  {
    "packageName": "@beautifulstore/money",
    "version": "latest",
    "timestamp": "2026-03-31T13:59:33.487Z"
  },
  {
    "packageName": "@b360/authenticator",
    "version": "latest",
    "timestamp": "2026-03-31T13:59:33.486Z"
  },
  {
    "packageName": "@azaeldragon/discord-embed-builder",
    "version": "latest",
    "timestamp": "2026-03-31T13:59:33.486Z"
  },
  {
    "packageName": "@axmit/redux-communications",
    "version": "latest",
    "timestamp": "2026-03-31T13:59:33.485Z"
  },
  {
    "packageName": "@ayame/quotes",
    "version": "latest",
    "timestamp": "2026-03-31T13:59:33.346Z"
  },
  {
    "packageName": "@atomist/sample-sdm",
    "version": "latest",
    "timestamp": "2026-03-31T13:59:33.345Z"
  },
  {
    "packageName": "@aspectus/vue-dropzone",
    "version": "latest",
    "timestamp": "2026-03-31T13:59:33.344Z"
  },
  {
    "packageName": "@ashlkv/vue-easy-dnd",
    "version": "latest",
    "timestamp": "2026-03-31T13:59:33.344Z"
  },
  {
    "packageName": "@alehuo/type-safe-storage",
    "version": "latest",
    "timestamp": "2026-03-31T13:59:33.343Z"
  },
  {
    "packageName": "@alancpazetto/commons",
    "version": "latest",
    "timestamp": "2026-03-31T13:59:33.343Z"
  },
  {
    "packageName": "@adaptabletools/adaptable-plugin-charts",
    "version": "latest",
    "timestamp": "2026-03-31T13:59:33.342Z"
  },
  {
    "packageName": "@7isys/loopback-component-passport",
    "version": "latest",
    "timestamp": "2026-03-31T13:59:33.342Z"
  },
  {
    "packageName": "@superbet-group/web.types",
    "version": "latest",
    "timestamp": "2026-03-31T13:59:32.086Z"
  },
  {
    "packageName": "@superbet-group/web.lib.vue-utilities",
    "version": "latest",
    "timestamp": "2026-03-31T13:59:31.935Z"
  },
  {
    "packageName": "@superbet-group/web.lib.config",
    "version": "latest",
    "timestamp": "2026-03-31T13:59:31.934Z"
  },
  {
    "packageName": "@superbet-group/allowances-js",
    "version": "latest",
    "timestamp": "2026-03-31T13:59:31.934Z"
  }
]