[
  {
    "packageName": "@hig/theme-data",
    "version": "latest",
    "timestamp": "2026-06-07T04:45:10.645Z"
  },
  {
    "packageName": "reactjs-charts",
    "version": "latest",
    "timestamp": "2026-06-07T04:45:10.645Z"
  },
  {
    "packageName": "react-native-testing-template",
    "version": "latest",
    "timestamp": "2026-06-07T04:45:10.644Z"
  },
  {
    "packageName": "rn-release-storyblok",
    "version": "latest",
    "timestamp": "2026-06-07T04:45:10.643Z"
  },
  {
    "packageName": "react-native-template-modular-structure",
    "version": "latest",
    "timestamp": "2026-06-07T04:45:10.643Z"
  },
  {
    "packageName": "react-native-template-karai",
    "version": "latest",
    "timestamp": "2026-06-07T04:45:10.642Z"
  },
  {
    "packageName": "moviez",
    "version": "latest",
    "timestamp": "2026-06-07T04:45:10.641Z"
  },
  {
    "packageName": "ical-chrome",
    "version": "latest",
    "timestamp": "2026-06-07T04:45:10.641Z"
  },
  {
    "packageName": "@reaxi/events",
    "version": "latest",
    "timestamp": "2026-06-07T04:45:10.640Z"
  },
  {
    "packageName": "import-core",
    "version": "latest",
    "timestamp": "2026-06-07T04:45:10.639Z"
  },
  {
    "packageName": "vue-libone-demo",
    "version": "latest",
    "timestamp": "2026-06-07T04:45:10.639Z"
  },
  {
    "packageName": "shadowizard-bfg",
    "version": "latest",
    "timestamp": "2026-06-07T04:45:10.638Z"
  },
  {
    "packageName": "privatestorage",
    "version": "latest",
    "timestamp": "2026-06-07T04:45:10.638Z"
  },
  {
    "packageName": "@nxg-org/mineflayer-jump-pathing",
    "version": "latest",
    "timestamp": "2026-06-07T04:45:10.637Z"
  },
  {
    "packageName": "react-hook-audio-recorder",
    "version": "latest",
    "timestamp": "2026-06-07T04:45:10.636Z"
  },
  {
    "packageName": "@inrixia/set-system-clock",
    "version": "latest",
    "timestamp": "2026-06-07T04:45:10.635Z"
  },
  {
    "packageName": "icon-commit",
    "version": "latest",
    "timestamp": "2026-06-07T04:45:10.635Z"
  },
  {
    "packageName": "@ygorluiz/react-use-size",
    "version": "latest",
    "timestamp": "2026-06-07T04:45:10.634Z"
  },
  {
    "packageName": "@ygorluiz/react-visually-hidden",
    "version": "latest",
    "timestamp": "2026-06-07T04:45:10.633Z"
  },
  {
    "packageName": "@ygorluiz/react-use-previous",
    "version": "latest",
    "timestamp": "2026-06-07T04:45:10.633Z"
  },
  {
    "packageName": "@ygorluiz/react-use-rect",
    "version": "latest",
    "timestamp": "2026-06-07T04:45:10.632Z"
  },
  {
    "packageName": "@ygorluiz/react-use-layout-effect",
    "version": "latest",
    "timestamp": "2026-06-07T04:45:10.631Z"
  },
  {
    "packageName": "@ygorluiz/react-use-escape-keydown",
    "version": "latest",
    "timestamp": "2026-06-07T04:45:10.631Z"
  },
  {
    "packageName": "@ygorluiz/react-use-callback-ref",
    "version": "latest",
    "timestamp": "2026-06-07T04:45:10.630Z"
  },
  {
    "packageName": "@ygorluiz/react-tooltip",
    "version": "latest",
    "timestamp": "2026-06-07T04:45:10.629Z"
  },
  {
    "packageName": "@ygorluiz/react-toolbar",
    "version": "latest",
    "timestamp": "2026-06-07T04:45:10.629Z"
  },
  {
    "packageName": "@ygorluiz/react-toggle-group",
    "version": "latest",
    "timestamp": "2026-06-07T04:45:10.628Z"
  },
  {
    "packageName": "@ygorluiz/react-toast",
    "version": "latest",
    "timestamp": "2026-06-07T04:45:10.628Z"
  },
  {
    "packageName": "@ygorluiz/react-toggle",
    "version": "latest",
    "timestamp": "2026-06-07T04:45:10.627Z"
  },
  {
    "packageName": "@ygorluiz/react-switch",
    "version": "latest",
    "timestamp": "2026-06-07T04:45:10.626Z"
  },
  {
    "packageName": "@ygorluiz/react-tabs",
    "version": "latest",
    "timestamp": "2026-06-07T04:45:10.626Z"
  },
  {
    "packageName": "@ygorluiz/react-slider",
    "version": "latest",
    "timestamp": "2026-06-07T04:45:10.625Z"
  },
  {
    "packageName": "@ygorluiz/react-slot",
    "version": "latest",
    "timestamp": "2026-06-07T04:45:10.624Z"
  },
  {
    "packageName": "@ygorluiz/react-separator",
    "version": "latest",
    "timestamp": "2026-06-07T04:45:10.624Z"
  },
  {
    "packageName": "@ygorluiz/react-select",
    "version": "latest",
    "timestamp": "2026-06-07T04:45:10.623Z"
  },
  {
    "packageName": "@ygorluiz/react-scroll-area",
    "version": "latest",
    "timestamp": "2026-06-07T04:45:10.622Z"
  },
  {
    "packageName": "@ygorluiz/react-roving-focus",
    "version": "latest",
    "timestamp": "2026-06-07T04:45:10.621Z"
  },
  {
    "packageName": "@ygorluiz/react-radio-group",
    "version": "latest",
    "timestamp": "2026-06-07T04:45:10.619Z"
  },
  {
    "packageName": "@ygorluiz/react-progress",
    "version": "latest",
    "timestamp": "2026-06-07T04:45:10.618Z"
  },
  {
    "packageName": "@ygorluiz/react-primitive",
    "version": "latest",
    "timestamp": "2026-06-07T04:45:10.617Z"
  },
  {
    "packageName": "@ygorluiz/react-portal",
    "version": "latest",
    "timestamp": "2026-06-07T04:45:10.617Z"
  },
  {
    "packageName": "@ygorluiz/react-popper",
    "version": "latest",
    "timestamp": "2026-06-07T04:45:10.616Z"
  },
  {
    "packageName": "@ygorluiz/react-presence",
    "version": "latest",
    "timestamp": "2026-06-07T04:45:10.615Z"
  },
  {
    "packageName": "@ygorluiz/react-popover",
    "version": "latest",
    "timestamp": "2026-06-07T04:45:10.615Z"
  },
  {
    "packageName": "@ygorluiz/react-navigation-menu",
    "version": "latest",
    "timestamp": "2026-06-07T04:45:10.614Z"
  },
  {
    "packageName": "@ygorluiz/react-menu",
    "version": "latest",
    "timestamp": "2026-06-07T04:45:10.613Z"
  },
  {
    "packageName": "@ygorluiz/react-label",
    "version": "latest",
    "timestamp": "2026-06-07T04:45:10.613Z"
  },
  {
    "packageName": "@ygorluiz/react-id",
    "version": "latest",
    "timestamp": "2026-06-07T04:45:10.612Z"
  },
  {
    "packageName": "@ygorluiz/react-hover-card",
    "version": "latest",
    "timestamp": "2026-06-07T04:45:10.611Z"
  },
  {
    "packageName": "@ygorluiz/react-focus-scope",
    "version": "latest",
    "timestamp": "2026-06-07T04:45:10.611Z"
  },
  {
    "packageName": "@ygorluiz/react-focus-guards",
    "version": "latest",
    "timestamp": "2026-06-07T04:45:10.610Z"
  },
  {
    "packageName": "@ygorluiz/react-dropdown-menu",
    "version": "latest",
    "timestamp": "2026-06-07T04:45:10.609Z"
  },
  {
    "packageName": "@ygorluiz/react-dismissable-layer",
    "version": "latest",
    "timestamp": "2026-06-07T04:45:10.609Z"
  },
  {
    "packageName": "@ygorluiz/react-direction",
    "version": "latest",
    "timestamp": "2026-06-07T04:45:10.608Z"
  },
  {
    "packageName": "@ygorluiz/react-dialog",
    "version": "latest",
    "timestamp": "2026-06-07T04:45:10.607Z"
  },
  {
    "packageName": "@ygorluiz/react-context-menu",
    "version": "latest",
    "timestamp": "2026-06-07T04:45:10.607Z"
  },
  {
    "packageName": "@ygorluiz/react-context",
    "version": "latest",
    "timestamp": "2026-06-07T04:45:10.606Z"
  },
  {
    "packageName": "@ygorluiz/react-compose-refs",
    "version": "latest",
    "timestamp": "2026-06-07T04:45:10.605Z"
  },
  {
    "packageName": "@ygorluiz/react-collection",
    "version": "latest",
    "timestamp": "2026-06-07T04:45:10.604Z"
  },
  {
    "packageName": "@ygorluiz/react-collapsible",
    "version": "latest",
    "timestamp": "2026-06-07T04:45:10.604Z"
  },
  {
    "packageName": "@ygorluiz/react-checkbox",
    "version": "latest",
    "timestamp": "2026-06-07T04:45:10.603Z"
  },
  {
    "packageName": "@ygorluiz/react-avatar",
    "version": "latest",
    "timestamp": "2026-06-07T04:45:10.602Z"
  },
  {
    "packageName": "@ygorluiz/react-aspect-ratio",
    "version": "latest",
    "timestamp": "2026-06-07T04:45:10.602Z"
  },
  {
    "packageName": "@ygorluiz/react-arrow",
    "version": "latest",
    "timestamp": "2026-06-07T04:45:10.601Z"
  },
  {
    "packageName": "@ygorluiz/react-announce",
    "version": "latest",
    "timestamp": "2026-06-07T04:45:10.601Z"
  },
  {
    "packageName": "@ygorluiz/react-alert-dialog",
    "version": "latest",
    "timestamp": "2026-06-07T04:45:10.600Z"
  },
  {
    "packageName": "@ygorluiz/react-accordion",
    "version": "latest",
    "timestamp": "2026-06-07T04:45:10.599Z"
  },
  {
    "packageName": "@ygorluiz/rect",
    "version": "latest",
    "timestamp": "2026-06-07T04:45:10.599Z"
  },
  {
    "packageName": "@ygorluiz/react-accessible-icon",
    "version": "latest",
    "timestamp": "2026-06-07T04:45:10.598Z"
  },
  {
    "packageName": "@ygorluiz/primitive",
    "version": "latest",
    "timestamp": "2026-06-07T04:45:10.597Z"
  },
  {
    "packageName": "@ygorluiz/number",
    "version": "latest",
    "timestamp": "2026-06-07T04:45:10.597Z"
  },
  {
    "packageName": "dsr-package-eosin-skies-paned-appro",
    "version": "latest",
    "timestamp": "2026-06-07T04:45:10.596Z"
  },
  {
    "packageName": "dsr-package-public-eosin-skies-paned-appro",
    "version": "latest",
    "timestamp": "2026-06-07T04:45:10.595Z"
  },
  {
    "packageName": "template-skeleton",
    "version": "latest",
    "timestamp": "2026-06-07T04:45:10.594Z"
  },
  {
    "packageName": "template-edify",
    "version": "latest",
    "timestamp": "2026-06-07T04:45:10.594Z"
  },
  {
    "packageName": "template-raptor",
    "version": "latest",
    "timestamp": "2026-06-07T04:45:10.593Z"
  },
  {
    "packageName": "template-moros",
    "version": "latest",
    "timestamp": "2026-06-07T04:45:10.592Z"
  },
  {
    "packageName": "avue-form-design",
    "version": "latest",
    "timestamp": "2026-06-07T04:45:10.592Z"
  },
  {
    "packageName": "@paybark/paybark-ui",
    "version": "latest",
    "timestamp": "2026-06-07T04:45:10.591Z"
  },
  {
    "packageName": "login-engels_valdez",
    "version": "latest",
    "timestamp": "2026-06-07T04:45:10.590Z"
  },
  {
    "packageName": "@design-automation/mobius-sim-funcs",
    "version": "latest",
    "timestamp": "2026-06-07T04:45:10.589Z"
  },
  {
    "packageName": "@design-automation/mobius-sim",
    "version": "latest",
    "timestamp": "2026-06-07T04:45:10.589Z"
  },
  {
    "packageName": "timezone-server",
    "version": "latest",
    "timestamp": "2026-06-07T04:45:10.588Z"
  },
  {
    "packageName": "react-native-orientation-locker-without-windows",
    "version": "latest",
    "timestamp": "2026-06-07T04:45:10.587Z"
  },
  {
    "packageName": "@seeker64/streak-counter",
    "version": "latest",
    "timestamp": "2026-06-07T04:45:10.587Z"
  },
  {
    "packageName": "strttohex",
    "version": "latest",
    "timestamp": "2026-06-07T04:45:10.586Z"
  },
  {
    "packageName": "@malagu/node-runtime-plugin",
    "version": "latest",
    "timestamp": "2026-06-07T04:45:10.585Z"
  },
  {
    "packageName": "solid-create",
    "version": "latest",
    "timestamp": "2026-06-07T04:45:10.585Z"
  },
  {
    "packageName": "markbeta",
    "version": "latest",
    "timestamp": "2026-06-07T04:45:10.583Z"
  },
  {
    "packageName": "github-test-two-three-four",
    "version": "latest",
    "timestamp": "2026-06-06T21:10:52.216Z"
  },
  {
    "packageName": "srn-cart-app-sample",
    "version": "latest",
    "timestamp": "2026-06-06T04:08:41.676Z"
  },
  {
    "packageName": "@universis/ngx-rules",
    "version": "latest",
    "timestamp": "2026-06-06T04:08:41.675Z"
  },
  {
    "packageName": "vue3-component-libraryyyy",
    "version": "latest",
    "timestamp": "2026-06-06T04:08:41.675Z"
  },
  {
    "packageName": "typecccccccccccc",
    "version": "latest",
    "timestamp": "2026-06-06T04:08:41.673Z"
  },
  {
    "packageName": "@iztiar/iztiar-pidusage",
    "version": "latest",
    "timestamp": "2026-03-31T13:59:33.995Z"
  },
  {
    "packageName": "@iztiar/iztiar-foundation",
    "version": "latest",
    "timestamp": "2026-03-31T13:59:33.995Z"
  },
  {
    "packageName": "@iztiar/iztiar-core-ui",
    "version": "latest",
    "timestamp": "2026-03-31T13:59:33.994Z"
  },
  {
    "packageName": "@iztiar/iztiar-core-cli",
    "version": "latest",
    "timestamp": "2026-03-31T13:59:33.993Z"
  },
  {
    "packageName": "@iztiar/iztiar-broker",
    "version": "latest",
    "timestamp": "2026-03-31T13:59:33.993Z"
  },
  {
    "packageName": "@internetguru/scrolltopable",
    "version": "latest",
    "timestamp": "2026-03-31T13:59:33.992Z"
  },
  {
    "packageName": "@inspired-agency/gatsby-awesome-pagination",
    "version": "latest",
    "timestamp": "2026-03-31T13:59:33.992Z"
  },
  {
    "packageName": "@innatical/allests",
    "version": "latest",
    "timestamp": "2026-03-31T13:59:33.991Z"
  },
  {
    "packageName": "@informatix8/gulp-saxon-xslt",
    "version": "latest",
    "timestamp": "2026-03-31T13:59:33.991Z"
  },
  {
    "packageName": "@imi-shared/shorthand-composer",
    "version": "latest",
    "timestamp": "2026-03-31T13:59:33.990Z"
  },
  {
    "packageName": "@hieunhit/easygettext",
    "version": "latest",
    "timestamp": "2026-03-31T13:59:33.990Z"
  },
  {
    "packageName": "@heydovetail/ui-components",
    "version": "latest",
    "timestamp": "2026-03-31T13:59:33.989Z"
  },
  {
    "packageName": "@heydovetail/tslint-config",
    "version": "latest",
    "timestamp": "2026-03-31T13:59:33.989Z"
  },
  {
    "packageName": "@heydovetail/svg-to-react",
    "version": "latest",
    "timestamp": "2026-03-31T13:59:33.988Z"
  },
  {
    "packageName": "@heydovetail/set",
    "version": "latest",
    "timestamp": "2026-03-31T13:59:33.988Z"
  },
  {
    "packageName": "@heydovetail/map",
    "version": "latest",
    "timestamp": "2026-03-31T13:59:33.987Z"
  },
  {
    "packageName": "@heydovetail/editorconfig",
    "version": "latest",
    "timestamp": "2026-03-31T13:59:33.987Z"
  },
  {
    "packageName": "@heydovetail/editor",
    "version": "latest",
    "timestamp": "2026-03-31T13:59:33.986Z"
  },
  {
    "packageName": "@heydovetail/dql",
    "version": "latest",
    "timestamp": "2026-03-31T13:59:33.986Z"
  },
  {
    "packageName": "@heydovetail/collector-react",
    "version": "latest",
    "timestamp": "2026-03-31T13:59:33.985Z"
  },
  {
    "packageName": "@heydovetail/assert",
    "version": "latest",
    "timestamp": "2026-03-31T13:59:33.985Z"
  },
  {
    "packageName": "@heydovetail/array",
    "version": "latest",
    "timestamp": "2026-03-31T13:59:33.984Z"
  },
  {
    "packageName": "@gzbapp/packages",
    "version": "latest",
    "timestamp": "2026-03-31T13:59:33.984Z"
  },
  {
    "packageName": "@glog/cli",
    "version": "latest",
    "timestamp": "2026-03-31T13:59:33.983Z"
  },
  {
    "packageName": "@gladysassistant/theme-optimized",
    "version": "latest",
    "timestamp": "2026-03-31T13:59:33.983Z"
  },
  {
    "packageName": "@genie-ai/genie-router",
    "version": "latest",
    "timestamp": "2026-03-31T13:59:33.982Z"
  },
  {
    "packageName": "@freestarcapital/collector-pipeline",
    "version": "latest",
    "timestamp": "2026-03-31T13:59:33.828Z"
  },
  {
    "packageName": "@forter/stylelint-config",
    "version": "latest",
    "timestamp": "2026-03-31T13:59:33.828Z"
  },
  {
    "packageName": "@forter/element",
    "version": "latest",
    "timestamp": "2026-03-31T13:59:33.827Z"
  },
  {
    "packageName": "@finn-no/toast",
    "version": "latest",
    "timestamp": "2026-03-31T13:59:33.827Z"
  },
  {
    "packageName": "@finn-no/fabric-component-classes",
    "version": "latest",
    "timestamp": "2026-03-31T13:59:33.826Z"
  },
  {
    "packageName": "@fictivekin/react-beautiful-dnd",
    "version": "latest",
    "timestamp": "2026-03-31T13:59:33.826Z"
  },
  {
    "packageName": "@fictivekin/growable-uint8-array",
    "version": "latest",
    "timestamp": "2026-03-31T13:59:33.825Z"
  },
  {
    "packageName": "@fictivekin/fk-sass",
    "version": "latest",
    "timestamp": "2026-03-31T13:59:33.825Z"
  },
  {
    "packageName": "@fictivekin/browserslist-config-fk",
    "version": "latest",
    "timestamp": "2026-03-31T13:59:33.824Z"
  },
  {
    "packageName": "@fatmatto/resultjs",
    "version": "latest",
    "timestamp": "2026-03-31T13:59:33.824Z"
  },
  {
    "packageName": "@farts/release-namer",
    "version": "latest",
    "timestamp": "2026-03-31T13:59:33.823Z"
  },
  {
    "packageName": "@fantasypoints/nunjucks-filter-moment",
    "version": "latest",
    "timestamp": "2026-03-31T13:59:33.822Z"
  },
  {
    "packageName": "@essense/iso-claim",
    "version": "latest",
    "timestamp": "2026-03-31T13:59:33.822Z"
  },
  {
    "packageName": "@epeejs/react-scroll-snap",
    "version": "latest",
    "timestamp": "2026-03-31T13:59:33.821Z"
  },
  {
    "packageName": "@eloge/utils",
    "version": "latest",
    "timestamp": "2026-03-31T13:59:33.821Z"
  },
  {
    "packageName": "@elgervb/eslint-config",
    "version": "latest",
    "timestamp": "2026-03-31T13:59:33.820Z"
  },
  {
    "packageName": "@effective/prettier",
    "version": "latest",
    "timestamp": "2026-03-31T13:59:33.820Z"
  },
  {
    "packageName": "@ecadagiani/reacttools",
    "version": "latest",
    "timestamp": "2026-03-31T13:59:33.819Z"
  },
  {
    "packageName": "@dsr-rollback-org-hover-owled-agios-situs/dsr-rollback-package-hover-owled-agios-situs",
    "version": "latest",
    "timestamp": "2026-03-31T13:59:33.818Z"
  },
  {
    "packageName": "@dragosbln/react-native-flatlist-alphabet-fixed",
    "version": "latest",
    "timestamp": "2026-03-31T13:59:33.818Z"
  },
  {
    "packageName": "@dplewis/react-material-ui-5-carousel",
    "version": "latest",
    "timestamp": "2026-03-31T13:59:33.817Z"
  },
  {
    "packageName": "@downunderctf/ducky",
    "version": "latest",
    "timestamp": "2026-03-31T13:59:33.680Z"
  },
  {
    "packageName": "@doob-ng/core",
    "version": "latest",
    "timestamp": "2026-03-31T13:59:33.680Z"
  },
  {
    "packageName": "@domp/next",
    "version": "latest",
    "timestamp": "2026-03-31T13:59:33.679Z"
  },
  {
    "packageName": "@digitalmaas/uuid-base62",
    "version": "latest",
    "timestamp": "2026-03-31T13:59:33.679Z"
  },
  {
    "packageName": "@deividfortuna/input-number",
    "version": "latest",
    "timestamp": "2026-03-31T13:59:33.678Z"
  },
  {
    "packageName": "@decoy9697/priority-queue",
    "version": "latest",
    "timestamp": "2026-03-31T13:59:33.678Z"
  },
  {
    "packageName": "@codice-progressio/express-brute-mongoose",
    "version": "latest",
    "timestamp": "2026-03-31T13:59:33.677Z"
  },
  {
    "packageName": "@chartiful/react-line-graph",
    "version": "latest",
    "timestamp": "2026-03-31T13:59:33.488Z"
  },
  {
    "packageName": "@by-association-only/concat-style-loader",
    "version": "latest",
    "timestamp": "2026-03-31T13:59:33.488Z"
  },
  {
    "packageName": "@bellini/api",
    "version": "latest",
    "timestamp": "2026-03-31T13:59:33.487Z"
  },
  {
    "packageName": "@beautifulstore/money",
    "version": "latest",
    "timestamp": "2026-03-31T13:59:33.487Z"
  },
  {
    "packageName": "@b360/authenticator",
    "version": "latest",
    "timestamp": "2026-03-31T13:59:33.486Z"
  },
  {
    "packageName": "@azaeldragon/discord-embed-builder",
    "version": "latest",
    "timestamp": "2026-03-31T13:59:33.486Z"
  },
  {
    "packageName": "@axmit/redux-communications",
    "version": "latest",
    "timestamp": "2026-03-31T13:59:33.485Z"
  },
  {
    "packageName": "@ayame/quotes",
    "version": "latest",
    "timestamp": "2026-03-31T13:59:33.346Z"
  },
  {
    "packageName": "@atomist/sample-sdm",
    "version": "latest",
    "timestamp": "2026-03-31T13:59:33.345Z"
  },
  {
    "packageName": "@aspectus/vue-dropzone",
    "version": "latest",
    "timestamp": "2026-03-31T13:59:33.344Z"
  },
  {
    "packageName": "@ashlkv/vue-easy-dnd",
    "version": "latest",
    "timestamp": "2026-03-31T13:59:33.344Z"
  },
  {
    "packageName": "@alehuo/type-safe-storage",
    "version": "latest",
    "timestamp": "2026-03-31T13:59:33.343Z"
  },
  {
    "packageName": "@alancpazetto/commons",
    "version": "latest",
    "timestamp": "2026-03-31T13:59:33.343Z"
  },
  {
    "packageName": "@adaptabletools/adaptable-plugin-charts",
    "version": "latest",
    "timestamp": "2026-03-31T13:59:33.342Z"
  },
  {
    "packageName": "@7isys/loopback-component-passport",
    "version": "latest",
    "timestamp": "2026-03-31T13:59:33.342Z"
  },
  {
    "packageName": "@superbet-group/web.types",
    "version": "latest",
    "timestamp": "2026-03-31T13:59:32.086Z"
  },
  {
    "packageName": "@superbet-group/web.lib.vue-utilities",
    "version": "latest",
    "timestamp": "2026-03-31T13:59:31.935Z"
  },
  {
    "packageName": "@superbet-group/web.lib.config",
    "version": "latest",
    "timestamp": "2026-03-31T13:59:31.934Z"
  },
  {
    "packageName": "@superbet-group/allowances-js",
    "version": "latest",
    "timestamp": "2026-03-31T13:59:31.934Z"
  }
]